.gitignore
LICENSE
MANIFEST.in
README.md
README.rst
setup.py
ProcessMappingScanner/__init__.py
ProcessMappingScanner/__init__.py~
ProcessMappingScanner.egg-info/PKG-INFO
ProcessMappingScanner.egg-info/SOURCES.txt
ProcessMappingScanner.egg-info/dependency_links.txt
ProcessMappingScanner.egg-info/top_level.txt
doc/ProcessMappingScanner.html
doc/index.html