Metadata-Version: 1.1
Name: ProcessMappingScanner
Version: 2.3.2
Summary: Python module for scanning information on running processes, including mappings, open file-descriptors, process owner, and other information
Home-page: https://github.com/kata198/ProcessMappingScanner
Author: Tim Savannah
Author-email: kata198@gmail.com
License: LGPLv3
Keywords: process,mapping,scanner,unix,proc,mappings,lib,detect,executable,shared,object,fd,filename,search,socket,descriptor,owner,pids,cwd
Platform: UNKNOWN
Classifier: Development Status :: 5 - Production/Stable
Classifier: Programming Language :: Python
Classifier: License :: OSI Approved :: GNU Lesser General Public License v3 (LGPLv3)
Classifier: Programming Language :: Python :: 2
Classifier: Programming Language :: Python :: 2
Classifier: Programming Language :: Python :: 2.7
Classifier: Programming Language :: Python :: 3
Classifier: Programming Language :: Python :: 3.3
Classifier: Programming Language :: Python :: 3.4
Classifier: Programming Language :: Python :: 3.5
Classifier: Programming Language :: Python :: 3.6
